sheets/__init__.py
sheets/client.py
myb_google_sheets_api-1.0.2.dist-info/LICENSE
myb_google_sheets_api-1.0.2.dist-info/METADATA
myb_google_sheets_api-1.0.2.dist-info/WHEEL
myb_google_sheets_api-1.0.2.dist-info/top_level.txt
myb_google_sheets_api-1.0.2.dist-info/RECORD
