Metadata-Version: 2.1
Name: myb-google-sheets-api
Version: 1.0.2
Summary: Python library for communicating with the Google Sheets API
Home-page: https://github.com/mine-your-business/myb-google-sheets-api
Author: Mine Your Business
Author-email: mine.your.business.crypto@gmail.com
License: GPL-3
Platform: UNKNOWN
Classifier: Programming Language :: Python :: 3
Classifier: License :: OSI Approved :: GNU General Public License v3 (GPLv3)
Classifier: Operating System :: OS Independent
Requires-Python: >=3.7
Requires-Dist: google-api-python-client (==1.12.8)
Requires-Dist: google-auth-httplib2 (==0.0.4)
Requires-Dist: google-auth-oauthlib (==0.4.2)
